charmonium/determ_hash/__init__.py
charmonium/determ_hash/lib.py
charmonium/determ_hash/py.typed
charmonium.determ_hash-0.2.2.dist-info/LICENSE
charmonium.determ_hash-0.2.2.dist-info/WHEEL
charmonium.determ_hash-0.2.2.dist-info/METADATA
charmonium.determ_hash-0.2.2.dist-info/RECORD
