Metadata-Version: 2.1
Name: charmonium.determ-hash
Version: 0.2.2
Summary: 
Home-page: https://github.com/charmoniumQ/charmonium.determ_hash.git
License: MIT
Keywords: deterministic,hash
Author: Samuel Grayson
Author-email: grayson5@illinois.edu
Requires-Python: >=3.7,<4.0
Classifier: Development Status :: 4 - Beta
Classifier: License :: OSI Approved :: MIT License
Classifier: Operating System :: OS Independent
Classifier: Programming Language :: Python :: 3
Classifier: Programming Language :: Python :: 3.10
Classifier: Programming Language :: Python :: 3.7
Classifier: Programming Language :: Python :: 3.8
Classifier: Programming Language :: Python :: 3.9
Classifier: Topic :: Software Development :: Libraries
Requires-Dist: xxhash (>=2.0.2,<3.0.0)
Project-URL: Repository, https://github.com/charmoniumQ/charmonium.determ_hash.git
